galgen/__init__.py
galgen/__main__.py
galgen/build.py
galgen/index.html.j2
galgen/init.py
galgen-0.2.0.dist-info/METADATA
galgen-0.2.0.dist-info/WHEEL
galgen-0.2.0.dist-info/entry_points.txt
galgen-0.2.0.dist-info/RECORD
